fuzzy_sentences_clustering/__init__.py
fuzzy_sentences_clustering/fuzzy_sentences_clustering.py
fuzzy_sentences_clustering-1.1.2.dist-info/WHEEL
fuzzy_sentences_clustering-1.1.2.dist-info/METADATA
fuzzy_sentences_clustering-1.1.2.dist-info/RECORD
