Metadata-Version: 2.1
Name: fuzzy-sentences-clustering
Version: 1.1.2
Summary: Clustering similar sentences based on their fuzzy similarity.
Home-page: https://github.com/SClovesgtx/fuzzy-sentences-clustering
License: MIT
Keywords: clusterization,fuzzy,similarity,text
Author: Cloves Paiva
Author-email: clovesgtx@gmail.com
Requires-Python: >=3.8,<4.0
Classifier: License :: OSI Approved :: MIT License
Classifier: Operating System :: OS Independent
Classifier: Programming Language :: Python :: 3
Classifier: Programming Language :: Python :: 3.10
Classifier: Programming Language :: Python :: 3.6
Classifier: Programming Language :: Python :: 3.7
Classifier: Programming Language :: Python :: 3.8
Classifier: Programming Language :: Python :: 3.9
Requires-Dist: fuzzywuzzy (==0.18.0)
Requires-Dist: nltk (==3.7)
Requires-Dist: python-Levenshtein-wheels (==0.13.2)
Project-URL: Repository, https://github.com/SClovesgtx/fuzzy-sentences-clustering
